<LiTable_General_Bien_conclusions>     <LiItem_table_General_Bien_conclusions>          <LiColonne_Id>0</LiColonne_Id>          <LiColonne_Index>0</LiColonne_Index>          <LiColonne_nom>Parasites</LiColonne_nom>          <LiColonne_manuelle></LiColonne_manuelle>          <LiColonne_mode_force></LiColonne_mode_force>          <LiColonne_conclusion></LiColonne_conclusion>          <LiColonne_conclusion_liciel></LiColonne_conclusion_liciel>          <LiColonne_date_fin_validite></LiColonne_date_fin_validite>          <LiColonne_date_fin_validite_liciel></LiColonne_date_fin_validite_liciel>          <LiColonne_xml></LiColonne_xml>     </LiItem_table_General_Bien_conclusions>     <LiItem_table_General_Bien_conclusions>          <LiColonne_Id>1</LiColonne_Id>          <LiColonne_Index>1</LiColonne_Index>          <LiColonne_nom></LiColonne_nom>          <LiColonne_manuelle></LiColonne_manuelle>          <LiColonne_mode_force></LiColonne_mode_force>          <LiColonne_conclusion></LiColonne_conclusion>          <LiColonne_conclusion_liciel></LiColonne_conclusion_liciel>          <LiColonne_date_fin_validite></LiColonne_date_fin_validite>          <LiColonne_date_fin_validite_liciel></LiColonne_date_fin_validite_liciel>          <LiColonne_xml></LiColonne_xml>     </LiItem_table_General_Bien_conclusions>     <LiItem_table_General_Bien_conclusions>          <LiColonne_Id>2</LiColonne_Id>          <LiColonne_Index>2</LiColonne_Index>          <LiColonne_nom></LiColonne_nom>          <LiColonne_manuelle></LiColonne_manuelle>          <LiColonne_mode_force></LiColonne_mode_force>          <LiColonne_conclusion></LiColonne_conclusion>          <LiColonne_conclusion_liciel></LiColonne_conclusion_liciel>          <LiColonne_date_fin_validite></LiColonne_date_fin_validite>          <LiColonne_date_fin_validite_liciel></LiColonne_date_fin_validite_liciel>          <LiColonne_xml></LiColonne_xml>     </LiItem_table_General_Bien_conclusions>     <LiItem_table_General_Bien_conclusions>          <LiColonne_Id>3</LiColonne_Id>          <LiColonne_Index>3</LiColonne_Index>          <LiColonne_nom></LiColonne_nom>          <LiColonne_manuelle></LiColonne_manuelle>          <LiColonne_mode_force></LiColonne_mode_force>          <LiColonne_conclusion></LiColonne_conclusion>          <LiColonne_conclusion_liciel></LiColonne_conclusion_liciel>          <LiColonne_date_fin_validite></LiColonne_date_fin_validite>          <LiColonne_date_fin_validite_liciel></LiColonne_date_fin_validite_liciel>          <LiColonne_xml></LiColonne_xml>     </LiItem_table_General_Bien_conclusions>     <LiItem_table_General_Bien_conclusions>          <LiColonne_Id>4</LiColonne_Id>          <LiColonne_Index>4</LiColonne_Index>          <LiColonne_nom></LiColonne_nom>          <LiColonne_manuelle></LiColonne_manuelle>          <LiColonne_mode_force></LiColonne_mode_force>          <LiColonne_conclusion></LiColonne_conclusion>          <LiColonne_conclusion_liciel></LiColonne_conclusion_liciel>          <LiColonne_date_fin_validite></LiColonne_date_fin_validite>          <LiColonne_date_fin_validite_liciel></LiColonne_date_fin_validite_liciel>          <LiColonne_xml></LiColonne_xml>     </LiItem_table_General_Bien_conclusions>     <LiItem_table_General_Bien_conclusions>          <LiColonne_Id>5</LiColonne_Id>          <LiColonne_Index>5</LiColonne_Index>          <LiColonne_nom>Carrez</LiColonne_nom>          <LiColonne_manuelle></LiColonne_manuelle>          <LiColonne_mode_force></LiColonne_mode_force>          <LiColonne_conclusion></LiColonne_conclusion>          <LiColonne_conclusion_liciel>Superficie Loi Carrez totale : 41,12 m²Surface au sol totale : 41,12 m²</LiColonne_conclusion_liciel>          <LiColonne_date_fin_validite></LiColonne_date_fin_validite>          <LiColonne_date_fin_validite_liciel></LiColonne_date_fin_validite_liciel>          <LiColonne_xml></LiColonne_xml>     </LiItem_table_General_Bien_conclusions>     <LiItem_table_General_Bien_conclusions>          <LiColonne_Id>6</LiColonne_Id>          <LiColonne_Index>6</LiColonne_Index>          <LiColonne_nom>Amiante</LiColonne_nom>          <LiColonne_manuelle></LiColonne_manuelle>          <LiColonne_mode_force></LiColonne_mode_force>          <LiColonne_conclusion></LiColonne_conclusion>          <LiColonne_conclusion_liciel>Dans le cadre de la mission, il n’a pas été repéré de matériaux et produits susceptibles de contenir de l'amiante.</LiColonne_conclusion_liciel>          <LiColonne_date_fin_validite></LiColonne_date_fin_validite>          <LiColonne_date_fin_validite_liciel></LiColonne_date_fin_validite_liciel>          <LiColonne_xml></LiColonne_xml>     </LiItem_table_General_Bien_conclusions>     <LiItem_table_General_Bien_conclusions>          <LiColonne_Id>7</LiColonne_Id>          <LiColonne_Index>7</LiColonne_Index>          <LiColonne_nom>Termites</LiColonne_nom>          <LiColonne_manuelle></LiColonne_manuelle>          <LiColonne_mode_force></LiColonne_mode_force>          <LiColonne_conclusion></LiColonne_conclusion>          <LiColonne_conclusion_liciel>Il n'a pas été repéré d'indice d'infestation de termites.</LiColonne_conclusion_liciel>          <LiColonne_date_fin_validite></LiColonne_date_fin_validite>          <LiColonne_date_fin_validite_liciel></LiColonne_date_fin_validite_liciel>          <LiColonne_xml></LiColonne_xml>     </LiItem_table_General_Bien_conclusions>     <LiItem_table_General_Bien_conclusions>          <LiColonne_Id>8</LiColonne_Id>          <LiColonne_Index>8</LiColonne_Index>          <LiColonne_nom>DPE</LiColonne_nom>          <LiColonne_manuelle></LiColonne_manuelle>          <LiColonne_mode_force></LiColonne_mode_force>          <LiColonne_conclusion></LiColonne_conclusion>          <LiColonne_conclusion_liciel>Consommation conventionnelle : 358 kWh ep/m².an (Classe F)Estimation des émissions : 74 kg eqCO2/m².an (Classe F)Estimation des coûts annuels : entre 1 190 € et 1 660 € par an, prix moyens des énergies indexés sur les années 2021, 2022, 2023Méthode : 3CL-DPE 2021N° ADEME : 2475E4088810Y</LiColonne_conclusion_liciel>          <LiColonne_date_fin_validite></LiColonne_date_fin_validite>          <LiColonne_date_fin_validite_liciel></LiColonne_date_fin_validite_liciel>          <LiColonne_xml></LiColonne_xml>     </LiItem_table_General_Bien_conclusions>     <LiItem_table_General_Bien_conclusions>          <LiColonne_Id>9</LiColonne_Id>          <LiColonne_Index>9</LiColonne_Index>          <LiColonne_nom>CREP</LiColonne_nom>          <LiColonne_manuelle></LiColonne_manuelle>          <LiColonne_mode_force></LiColonne_mode_force>          <LiColonne_conclusion></LiColonne_conclusion>          <LiColonne_conclusion_liciel></LiColonne_conclusion_liciel>          <LiColonne_date_fin_validite></LiColonne_date_fin_validite>          <LiColonne_date_fin_validite_liciel></LiColonne_date_fin_validite_liciel>          <LiColonne_xml></LiColonne_xml>     </LiItem_table_General_Bien_conclusions>     <LiItem_table_General_Bien_conclusions>          <LiColonne_Id>10</LiColonne_Id>          <LiColonne_Index>10</LiColonne_Index>          <LiColonne_nom>Gaz</LiColonne_nom>          <LiColonne_manuelle></LiColonne_manuelle>          <LiColonne_mode_force></LiColonne_mode_force>          <LiColonne_conclusion></LiColonne_conclusion>          <LiColonne_conclusion_liciel></LiColonne_conclusion_liciel>          <LiColonne_date_fin_validite></LiColonne_date_fin_validite>          <LiColonne_date_fin_validite_liciel></LiColonne_date_fin_validite_liciel>          <LiColonne_xml></LiColonne_xml>     </LiItem_table_General_Bien_conclusions>     <LiItem_table_General_Bien_conclusions>          <LiColonne_Id>11</LiColonne_Id>          <LiColonne_Index>11</LiColonne_Index>          <LiColonne_nom>PTZ</LiColonne_nom>          <LiColonne_manuelle></LiColonne_manuelle>          <LiColonne_mode_force></LiColonne_mode_force>          <LiColonne_conclusion></LiColonne_conclusion>          <LiColonne_conclusion_liciel></LiColonne_conclusion_liciel>          <LiColonne_date_fin_validite></LiColonne_date_fin_validite>          <LiColonne_date_fin_validite_liciel></LiColonne_date_fin_validite_liciel>          <LiColonne_xml></LiColonne_xml>     </LiItem_table_General_Bien_conclusions>     <LiItem_table_General_Bien_conclusions>          <LiColonne_Id>12</LiColonne_Id>          <LiColonne_Index>12</LiColonne_Index>          <LiColonne_nom>ERNT</LiColonne_nom>          <LiColonne_manuelle></LiColonne_manuelle>          <LiColonne_mode_force></LiColonne_mode_force>          <LiColonne_conclusion></LiColonne_conclusion>          <LiColonne_conclusion_liciel>Le bien est situé dans le périmètre d'un plan de prévention des risques naturels (Mouvement de terrain, Autres: Zone comportant des poches de gypse antéludien (PPRn), anciennes carrières)Le bien n'est pas situé dans le périmètre d'un plan de prévention des risques miniersLe bien n'est pas situé dans le périmètre d'un plan de prévention des risques technologiquesZone sismique définie en zone 1 selon la règlementation parasismique 2011ENSA : L’immeuble n'est pas concerné par un plan d'exposition aux bruitsENSA : Aucune nuisance aérienne n'a été identifiée sur le bien</LiColonne_conclusion_liciel>          <LiColonne_date_fin_validite></LiColonne_date_fin_validite>          <LiColonne_date_fin_validite_liciel></LiColonne_date_fin_validite_liciel>          <LiColonne_xml></LiColonne_xml>     </LiItem_table_General_Bien_conclusions>     <LiItem_table_General_Bien_conclusions>          <LiColonne_Id>13</LiColonne_Id>          <LiColonne_Index>13</LiColonne_Index>          <LiColonne_nom>Assainissement</LiColonne_nom>          <LiColonne_manuelle></LiColonne_manuelle>          <LiColonne_mode_force></LiColonne_mode_force>          <LiColonne_conclusion></LiColonne_conclusion>          <LiColonne_conclusion_liciel></LiColonne_conclusion_liciel>          <LiColonne_date_fin_validite></LiColonne_date_fin_validite>          <LiColonne_date_fin_validite_liciel></LiColonne_date_fin_validite_liciel>          <LiColonne_xml></LiColonne_xml>     </LiItem_table_General_Bien_conclusions>     <LiItem_table_General_Bien_conclusions>          <LiColonne_Id>14</LiColonne_Id>          <LiColonne_Index>14</LiColonne_Index>          <LiColonne_nom>Piscine</LiColonne_nom>          <LiColonne_manuelle></LiColonne_manuelle>          <LiColonne_mode_force></LiColonne_mode_force>          <LiColonne_conclusion></LiColonne_conclusion>          <LiColonne_conclusion_liciel></LiColonne_conclusion_liciel>          <LiColonne_date_fin_validite></LiColonne_date_fin_validite>          <LiColonne_date_fin_validite_liciel></LiColonne_date_fin_validite_liciel>          <LiColonne_xml></LiColonne_xml>     </LiItem_table_General_Bien_conclusions>     <LiItem_table_General_Bien_conclusions>          <LiColonne_Id>15</LiColonne_Id>          <LiColonne_Index>15</LiColonne_Index>          <LiColonne_nom>DTG</LiColonne_nom>          <LiColonne_manuelle></LiColonne_manuelle>          <LiColonne_mode_force></LiColonne_mode_force>          <LiColonne_conclusion></LiColonne_conclusion>          <LiColonne_conclusion_liciel></LiColonne_conclusion_liciel>          <LiColonne_date_fin_validite></LiColonne_date_fin_validite>          <LiColonne_date_fin_validite_liciel></LiColonne_date_fin_validite_liciel>          <LiColonne_xml></LiColonne_xml>     </LiItem_table_General_Bien_conclusions>     <LiItem_table_General_Bien_conclusions>          <LiColonne_Id>16</LiColonne_Id>          <LiColonne_Index>16</LiColonne_Index>          <LiColonne_nom>Radon</LiColonne_nom>          <LiColonne_manuelle></LiColonne_manuelle>          <LiColonne_mode_force></LiColonne_mode_force>          <LiColonne_conclusion></LiColonne_conclusion>          <LiColonne_conclusion_liciel></LiColonne_conclusion_liciel>          <LiColonne_date_fin_validite></LiColonne_date_fin_validite>          <LiColonne_date_fin_validite_liciel></LiColonne_date_fin_validite_liciel>          <LiColonne_xml></LiColonne_xml>     </LiItem_table_General_Bien_conclusions>     <LiItem_table_General_Bien_conclusions>          <LiColonne_Id>17</LiColonne_Id>          <LiColonne_Index>17</LiColonne_Index>          <LiColonne_nom>Ascenseur</LiColonne_nom>          <LiColonne_manuelle></LiColonne_manuelle>          <LiColonne_mode_force></LiColonne_mode_force>          <LiColonne_conclusion></LiColonne_conclusion>          <LiColonne_conclusion_liciel></LiColonne_conclusion_liciel>          <LiColonne_date_fin_validite></LiColonne_date_fin_validite>          <LiColonne_date_fin_validite_liciel></LiColonne_date_fin_validite_liciel>          <LiColonne_xml></LiColonne_xml>     </LiItem_table_General_Bien_conclusions>     <LiItem_table_General_Bien_conclusions>          <LiColonne_Id>18</LiColonne_Id>          <LiColonne_Index>18</LiColonne_Index>          <LiColonne_nom>Electricité</LiColonne_nom>          <LiColonne_manuelle></LiColonne_manuelle>          <LiColonne_mode_force></LiColonne_mode_force>          <LiColonne_conclusion></LiColonne_conclusion>          <LiColonne_conclusion_liciel>L'installation intérieure d'électricité comporte une ou des anomalies pour laquelle ou lesquelles il est vivement recommandé d'agir afin d'éliminer les dangers qu'elle(s) présente(nt).</LiColonne_conclusion_liciel>          <LiColonne_date_fin_validite></LiColonne_date_fin_validite>          <LiColonne_date_fin_validite_liciel></LiColonne_date_fin_validite_liciel>          <LiColonne_xml></LiColonne_xml>     </LiItem_table_General_Bien_conclusions>     <LiItem_table_General_Bien_conclusions>          <LiColonne_Id>19</LiColonne_Id>          <LiColonne_Index>19</LiColonne_Index>          <LiColonne_nom>Etat Habitabilité</LiColonne_nom>          <LiColonne_manuelle></LiColonne_manuelle>          <LiColonne_mode_force></LiColonne_mode_force>          <LiColonne_conclusion></LiColonne_conclusion>          <LiColonne_conclusion_liciel></LiColonne_conclusion_liciel>          <LiColonne_date_fin_validite></LiColonne_date_fin_validite>          <LiColonne_date_fin_validite_liciel></LiColonne_date_fin_validite_liciel>          <LiColonne_xml></LiColonne_xml>     </LiItem_table_General_Bien_conclusions>     <LiItem_table_General_Bien_conclusions>          <LiColonne_Id>20</LiColonne_Id>          <LiColonne_Index>20</LiColonne_Index>          <LiColonne_nom></LiColonne_nom>          <LiColonne_manuelle></LiColonne_manuelle>          <LiColonne_mode_force></LiColonne_mode_force>          <LiColonne_conclusion></LiColonne_conclusion>          <LiColonne_conclusion_liciel></LiColonne_conclusion_liciel>          <LiColonne_date_fin_validite></LiColonne_date_fin_validite>          <LiColonne_date_fin_validite_liciel></LiColonne_date_fin_validite_liciel>          <LiColonne_xml></LiColonne_xml>     </LiItem_table_General_Bien_conclusions>     <LiItem_table_General_Bien_conclusions>          <LiColonne_Id>21</LiColonne_Id>          <LiColonne_Index>21</LiColonne_Index>          <LiColonne_nom>Etat des lieux</LiColonne_nom>          <LiColonne_manuelle></LiColonne_manuelle>          <LiColonne_mode_force></LiColonne_mode_force>          <LiColonne_conclusion></LiColonne_conclusion>          <LiColonne_conclusion_liciel></LiColonne_conclusion_liciel>          <LiColonne_date_fin_validite></LiColonne_date_fin_validite>          <LiColonne_date_fin_validite_liciel></LiColonne_date_fin_validite_liciel>          <LiColonne_xml></LiColonne_xml>     </LiItem_table_General_Bien_conclusions>     <LiItem_table_General_Bien_conclusions>          <LiColonne_Id>22</LiColonne_Id>          <LiColonne_Index>22</LiColonne_Index>          <LiColonne_nom>Incendie</LiColonne_nom>          <LiColonne_manuelle></LiColonne_manuelle>          <LiColonne_mode_force></LiColonne_mode_force>          <LiColonne_conclusion></LiColonne_conclusion>          <LiColonne_conclusion_liciel></LiColonne_conclusion_liciel>          <LiColonne_date_fin_validite></LiColonne_date_fin_validite>          <LiColonne_date_fin_validite_liciel></LiColonne_date_fin_validite_liciel>          <LiColonne_xml></LiColonne_xml>     </LiItem_table_General_Bien_conclusions>     <LiItem_table_General_Bien_conclusions>          <LiColonne_Id>23</LiColonne_Id>          <LiColonne_Index>23</LiColonne_Index>          <LiColonne_nom>Handicapé</LiColonne_nom>          <LiColonne_manuelle></LiColonne_manuelle>          <LiColonne_mode_force></LiColonne_mode_force>          <LiColonne_conclusion></LiColonne_conclusion>          <LiColonne_conclusion_liciel></LiColonne_conclusion_liciel>          <LiColonne_date_fin_validite></LiColonne_date_fin_validite>          <LiColonne_date_fin_validite_liciel></LiColonne_date_fin_validite_liciel>          <LiColonne_xml></LiColonne_xml>     </LiItem_table_General_Bien_conclusions>     <LiItem_table_General_Bien_conclusions>          <LiColonne_Id>24</LiColonne_Id>          <LiColonne_Index>24</LiColonne_Index>          <LiColonne_nom>Plomb dans l'eau</LiColonne_nom>          <LiColonne_manuelle></LiColonne_manuelle>          <LiColonne_mode_force></LiColonne_mode_force>          <LiColonne_conclusion></LiColonne_conclusion>          <LiColonne_conclusion_liciel></LiColonne_conclusion_liciel>          <LiColonne_date_fin_validite></LiColonne_date_fin_validite>          <LiColonne_date_fin_validite_liciel></LiColonne_date_fin_validite_liciel>          <LiColonne_xml></LiColonne_xml>     </LiItem_table_General_Bien_conclusions></LiTable_General_Bien_conclusions>